AUTHORS
INSTALL
LICENSE
MANIFEST.in
README.md
setup.py
celerytest/__init__.py
celerytest/config.py
celerytest/testcase.py
celerytest/tests.py
celerytest/worker.py
celerytest.egg-info/PKG-INFO
celerytest.egg-info/SOURCES.txt
celerytest.egg-info/dependency_links.txt
celerytest.egg-info/not-zip-safe
celerytest.egg-info/requires.txt
celerytest.egg-info/top_level.txt