Metadata-Version: 1.1
Name: celerytest
Version: 0.1.1
Summary: Run a monitored Celery worker for integration tests that depend on Celery tasks
Home-page: http://github.com/RentMethod/celerytest
Author: Willem Bult
Author-email: willem.bult@gmail.com
License: BSD license, see LICENSE
Download-URL: https://github.com/RentMethod/celerytest/archive/0.1.1.tar.gz
Keywords: celery,testing,integration,test
Platform: UNKNOWN
